[{"Year":1967,"Attendance":137492,"TV Viewers":51180000,"Streaming":0,"Spanish":0,"Out Of Home":0,"Total":51317492},{"Year":1968,"Attendance":75546,"TV Viewers":39120000,"Streaming":0,"Spanish":0,"Out Of Home":0,"Total":39195546},{"Year":1969,"Attendance":75389,"TV Viewers":41660000,"Streaming":0,"Spanish":0,"Out Of Home":0,"Total":41735389},{"Year":1970,"Attendance":80562,"TV Viewers":44270000,"Streaming":0,"Spanish":0,"Out Of Home":0,"Total":44350562},{"Year":1971,"Attendance":79204,"TV Viewers":46040000,"Streaming":0,"Spanish":0,"Out Of Home":0,"Total":46119204},{"Year":1972,"Attendance":81023,"TV Viewers":56640000,"Streaming":0,"Spanish":0,"Out Of Home":0,"Total":56721023},{"Year":1973,"Attendance":90182,"TV Viewers":53320000,"Streaming":0,"Spanish":0,"Out Of Home":0,"Total":53410182},{"Year":1974,"Attendance":71882,"TV Viewers":51700000,"Streaming":0,"Spanish":0,"Out Of Home":0,"Total":51771882},{"Year":1975,"Attendance":80997,"TV Viewers":56050000,"Streaming":0,"Spanish":0,"Out Of Home":0,"Total":56130997},{"Year":1976,"Attendance":80187,"TV Viewers":57710000,"Streaming":0,"Spanish":0,"Out Of Home":0,"Total":57790187},{"Year":1977,"Attendance":103438,"TV Viewers":62050000,"Streaming":0,"Spanish":0,"Out Of Home":0,"Total":62153438},{"Year":1978,"Attendance":76400,"TV Viewers":78940000,"Streaming":0,"Spanish":0,"Out Of Home":0,"Total":79016400},{"Year":1979,"Attendance":79484,"TV Viewers":74740000,"Streaming":0,"Spanish":0,"Out Of Home":0,"Total":74819484},{"Year":1980,"Attendance":103985,"TV Viewers":76240000,"Streaming":0,"Spanish":0,"Out Of Home":0,"Total":76343985},{"Year":1981,"Attendance":76135,"TV Viewers":68290000,"Streaming":0,"Spanish":0,"Out Of Home":0,"Total":68366135},{"Year":1982,"Attendance":81270,"TV Viewers":85240000,"Streaming":0,"Spanish":0,"Out Of Home":0,"Total":85321270},{"Year":1983,"Attendance":103667,"TV Viewers":81770000,"Streaming":0,"Spanish":0,"Out Of Home":0,"Total":81873667},{"Year":1984,"Attendance":72920,"TV Viewers":77620000,"Streaming":0,"Spanish":0,"Out Of Home":0,"Total":77692920},{"Year":1985,"Attendance":84059,"TV Viewers":85530000,"Streaming":0,"Spanish":0,"Out Of Home":0,"Total":85614059},{"Year":1986,"Attendance":73818,"TV Viewers":92570000,"Streaming":0,"Spanish":0,"Out Of Home":0,"Total":92643818},{"Year":1987,"Attendance":101063,"TV Viewers":87190000,"Streaming":0,"Spanish":0,"Out Of Home":0,"Total":87291063},{"Year":1988,"Attendance":73302,"TV Viewers":80140000,"Streaming":0,"Spanish":0,"Out Of Home":0,"Total":80213302},{"Year":1989,"Attendance":75129,"TV Viewers":81590000,"Streaming":0,"Spanish":0,"Out Of Home":0,"Total":81665129},{"Year":1990,"Attendance":72919,"TV Viewers":73850000,"Streaming":0,"Spanish":0,"Out Of Home":0,"Total":73922919},{"Year":1991,"Attendance":73813,"TV Viewers":79510000,"Streaming":0,"Spanish":0,"Out Of Home":0,"Total":79583813},{"Year":1992,"Attendance":63130,"TV Viewers":79590000,"Streaming":0,"Spanish":0,"Out Of Home":0,"Total":79653130},{"Year":1993,"Attendance":98374,"TV Viewers":90990000,"Streaming":0,"Spanish":0,"Out Of Home":0,"Total":91088374},{"Year":1994,"Attendance":72817,"TV Viewers":90000000,"Streaming":0,"Spanish":0,"Out Of Home":0,"Total":90072817},{"Year":1995,"Attendance":74107,"TV Viewers":83420000,"Streaming":0,"Spanish":0,"Out Of Home":0,"Total":83494107},{"Year":1996,"Attendance":76347,"TV Viewers":94080000,"Streaming":0,"Spanish":0,"Out Of Home":0,"Total":94156347},{"Year":1997,"Attendance":72301,"TV Viewers":87870000,"Streaming":0,"Spanish":0,"Out Of Home":0,"Total":87942301},{"Year":1998,"Attendance":68912,"TV Viewers":90000000,"Streaming":0,"Spanish":0,"Out Of Home":0,"Total":90068912},{"Year":1999,"Attendance":74803,"TV Viewers":83720000,"Streaming":0,"Spanish":0,"Out Of Home":0,"Total":83794803},{"Year":2000,"Attendance":72625,"TV Viewers":88470000,"Streaming":0,"Spanish":0,"Out Of Home":0,"Total":88542625},{"Year":2001,"Attendance":71921,"TV Viewers":84340000,"Streaming":0,"Spanish":0,"Out Of Home":0,"Total":84411921},{"Year":2002,"Attendance":72922,"TV Viewers":86800000,"Streaming":0,"Spanish":0,"Out Of Home":0,"Total":86872922},{"Year":2003,"Attendance":67603,"TV Viewers":88640000,"Streaming":0,"Spanish":0,"Out Of Home":0,"Total":88707603},{"Year":2004,"Attendance":71525,"TV Viewers":89800000,"Streaming":0,"Spanish":0,"Out Of Home":0,"Total":89871525},{"Year":2005,"Attendance":78125,"TV Viewers":86070000,"Streaming":0,"Spanish":0,"Out Of Home":0,"Total":86148125},{"Year":2006,"Attendance":68206,"TV Viewers":90750000,"Streaming":0,"Spanish":0,"Out Of Home":0,"Total":90818206},{"Year":2007,"Attendance":74512,"TV Viewers":93180000,"Streaming":0,"Spanish":0,"Out Of Home":0,"Total":93254512},{"Year":2008,"Attendance":71101,"TV Viewers":97450000,"Streaming":0,"Spanish":0,"Out Of Home":0,"Total":97521101},{"Year":2009,"Attendance":70774,"TV Viewers":98730000,"Streaming":0,"Spanish":0,"Out Of Home":0,"Total":98800774},{"Year":2010,"Attendance":74059,"TV Viewers":106480000,"Streaming":0,"Spanish":0,"Out Of Home":0,"Total":106554059},{"Year":2011,"Attendance":103219,"TV Viewers":111010000,"Streaming":0,"Spanish":0,"Out Of Home":0,"Total":111113219},{"Year":2012,"Attendance":68658,"TV Viewers":111350000,"Streaming":346000,"Spanish":0,"Out Of Home":0,"Total":111764658},{"Year":2013,"Attendance":71024,"TV Viewers":108690000,"Streaming":508000,"Spanish":0,"Out Of Home":0,"Total":109269024},{"Year":2014,"Attendance":82529,"TV Viewers":112190000,"Streaming":531000,"Spanish":561000,"Out Of Home":0,"Total":113364529},{"Year":2015,"Attendance":70288,"TV Viewers":114440000,"Streaming":973000,"Spanish":368000,"Out Of Home":0,"Total":115851288},{"Year":2016,"Attendance":71088,"TV Viewers":111860000,"Streaming":1400000,"Spanish":472000,"Out Of Home":0,"Total":113803088},{"Year":2017,"Attendance":70807,"TV Viewers":111320000,"Streaming":1720000,"Spanish":650000,"Out Of Home":0,"Total":113760807},{"Year":2018,"Attendance":67612,"TV Viewers":103390000,"Streaming":2020000,"Spanish":543000,"Out Of Home":12000000,"Total":118020612},{"Year":2019,"Attendance":70081,"TV Viewers":98190000,"Streaming":2600000,"Spanish":473000,"Out Of Home":12000000,"Total":113333081},{"Year":2020,"Attendance":62417,"TV Viewers":100450000,"Streaming":3400000,"Spanish":757000,"Out Of Home":13000000,"Total":117669417}]